{
    "1": {
        "y": 842, 
        "x": 546, 
        "height": 91, 
        "width": 46
    }, 
    "$": {
        "y": 751, 
        "x": 220, 
        "height": 91, 
        "width": 46
    }, 
    "(": {
        "y": 751, 
        "x": 391, 
        "height": 91, 
        "width": 28
    }, 
    ",": {
        "y": 842, 
        "x": 960, 
        "height": 91, 
        "width": 23
    }, 
    "0": {
        "y": 842, 
        "x": 500, 
        "height": 91, 
        "width": 46
    }, 
    "4": {
        "y": 842, 
        "x": 684, 
        "height": 91, 
        "width": 46
    }, 
    "8": {
        "y": 842, 
        "x": 868, 
        "height": 91, 
        "width": 46
    }, 
    "@": {
        "y": 751, 
        "x": 92, 
        "height": 91, 
        "width": 82
    }, 
    "D": {
        "y": 1024, 
        "x": 169, 
        "height": 91, 
        "width": 59
    }, 
    "H": {
        "y": 1024, 
        "x": 395, 
        "height": 91, 
        "width": 59
    }, 
    "L": {
        "y": 1024, 
        "x": 573, 
        "height": 91, 
        "width": 46
    }, 
    "P": {
        "y": 1024, 
        "x": 809, 
        "height": 91, 
        "width": 54
    }, 
    "T": {
        "y": 933, 
        "x": 54, 
        "height": 91, 
        "width": 50
    }, 
    "X": {
        "y": 933, 
        "x": 294, 
        "height": 91, 
        "width": 54
    }, 
    "\\": {
        "y": 751, 
        "x": 909, 
        "height": 91, 
        "width": 24
    }, 
    "&gt;": {
        "y": 751, 
        "x": 638, 
        "height": 91, 
        "width": 48
    }, 
    "d": {
        "y": 933, 
        "x": 585, 
        "height": 91, 
        "width": 46
    }, 
    "h": {
        "y": 933, 
        "x": 749, 
        "height": 91, 
        "width": 46
    }, 
    "l": {
        "y": 933, 
        "x": 878, 
        "height": 91, 
        "width": 19
    }, 
    "p": {
        "y": 842, 
        "x": 46, 
        "height": 91, 
        "width": 46
    }, 
    "t": {
        "y": 842, 
        "x": 208, 
        "height": 91, 
        "width": 23
    }, 
    "x": {
        "y": 842, 
        "x": 377, 
        "height": 91, 
        "width": 41
    }, 
    "#": {
        "y": 751, 
        "x": 174, 
        "height": 91, 
        "width": 46
    }, 
    "+": {
        "y": 751, 
        "x": 742, 
        "height": 91, 
        "width": 48
    }, 
    "/": {
        "y": 751, 
        "x": 566, 
        "height": 91, 
        "width": 24
    }, 
    "3": {
        "y": 842, 
        "x": 638, 
        "height": 91, 
        "width": 46
    }, 
    "7": {
        "y": 842, 
        "x": 822, 
        "height": 91, 
        "width": 46
    }, 
    ";": {
        "y": 751, 
        "x": 790, 
        "height": 91, 
        "width": 23
    }, 
    "?": {
        "y": 751, 
        "x": 46, 
        "height": 91, 
        "width": 46
    }, 
    "C": {
        "y": 1024, 
        "x": 110, 
        "height": 91, 
        "width": 59
    }, 
    "G": {
        "y": 1024, 
        "x": 332, 
        "height": 91, 
        "width": 63
    }, 
    "K": {
        "y": 1024, 
        "x": 518, 
        "height": 91, 
        "width": 55
    }, 
    "O": {
        "y": 1024, 
        "x": 746, 
        "height": 91, 
        "width": 63
    }, 
    "S": {
        "y": 933, 
        "x": 0, 
        "height": 91, 
        "width": 54
    }, 
    "W": {
        "y": 933, 
        "x": 217, 
        "height": 91, 
        "width": 77
    }, 
    "[": {
        "y": 751, 
        "x": 447, 
        "height": 91, 
        "width": 23
    }, 
    "_": {
        "y": 751, 
        "x": 933, 
        "height": 91, 
        "width": 49
    }, 
    "c": {
        "y": 933, 
        "x": 544, 
        "height": 91, 
        "width": 41
    }, 
    "g": {
        "y": 933, 
        "x": 703, 
        "height": 91, 
        "width": 46
    }, 
    "k": {
        "y": 933, 
        "x": 837, 
        "height": 91, 
        "width": 41
    }, 
    "o": {
        "y": 842, 
        "x": 0, 
        "height": 91, 
        "width": 46
    }, 
    "s": {
        "y": 842, 
        "x": 167, 
        "height": 91, 
        "width": 41
    }, 
    "w": {
        "y": 842, 
        "x": 318, 
        "height": 91, 
        "width": 59
    }, 
    "{": {
        "y": 751, 
        "x": 686, 
        "height": 91, 
        "width": 28
    }, 
    "&amp;": {
        "y": 751, 
        "x": 305, 
        "height": 91, 
        "width": 54
    }, 
    "*": {
        "y": 751, 
        "x": 359, 
        "height": 91, 
        "width": 32
    }, 
    ".": {
        "y": 842, 
        "x": 983, 
        "height": 91, 
        "width": 23
    }, 
    "2": {
        "y": 842, 
        "x": 592, 
        "height": 91, 
        "width": 46
    }, 
    "&lt;": {
        "y": 751, 
        "x": 590, 
        "height": 91, 
        "width": 48
    }, 
    "6": {
        "y": 842, 
        "x": 776, 
        "height": 91, 
        "width": 46
    }, 
    ":": {
        "y": 751, 
        "x": 0, 
        "height": 91, 
        "width": 23
    }, 
    "B": {
        "y": 1024, 
        "x": 56, 
        "height": 91, 
        "width": 54
    }, 
    "F": {
        "y": 1024, 
        "x": 282, 
        "height": 91, 
        "width": 50
    }, 
    "J": {
        "y": 1024, 
        "x": 477, 
        "height": 91, 
        "width": 41
    }, 
    "N": {
        "y": 1024, 
        "x": 687, 
        "height": 91, 
        "width": 59
    }, 
    "R": {
        "y": 1024, 
        "x": 926, 
        "height": 91, 
        "width": 59
    }, 
    "V": {
        "y": 933, 
        "x": 163, 
        "height": 91, 
        "width": 54
    }, 
    "Z": {
        "y": 933, 
        "x": 402, 
        "height": 91, 
        "width": 50
    }, 
    "^": {
        "y": 751, 
        "x": 266, 
        "height": 91, 
        "width": 39
    }, 
    "b": {
        "y": 933, 
        "x": 498, 
        "height": 91, 
        "width": 46
    }, 
    "f": {
        "y": 933, 
        "x": 677, 
        "height": 91, 
        "width": 26
    }, 
    "j": {
        "y": 933, 
        "x": 814, 
        "height": 91, 
        "width": 23
    }, 
    "n": {
        "y": 933, 
        "x": 965, 
        "height": 91, 
        "width": 46
    }, 
    "r": {
        "y": 842, 
        "x": 138, 
        "height": 91, 
        "width": 29
    }, 
    "v": {
        "y": 842, 
        "x": 277, 
        "height": 91, 
        "width": 41
    }, 
    "z": {
        "y": 842, 
        "x": 459, 
        "height": 91, 
        "width": 41
    }, 
    "~": {
        "y": 751, 
        "x": 861, 
        "height": 91, 
        "width": 48
    }, 
    "&quot;": {
        "y": 751, 
        "x": 493, 
        "height": 91, 
        "width": 29
    }, 
    "!": {
        "y": 751, 
        "x": 23, 
        "height": 91, 
        "width": 23
    }, 
    ")": {
        "y": 751, 
        "x": 419, 
        "height": 91, 
        "width": 28
    }, 
    "-": {
        "y": 751, 
        "x": 538, 
        "height": 91, 
        "width": 28
    }, 
    "&apos;": {
        "y": 751, 
        "x": 522, 
        "height": 91, 
        "width": 16
    }, 
    "5": {
        "y": 842, 
        "x": 730, 
        "height": 91, 
        "width": 46
    }, 
    "9": {
        "y": 842, 
        "x": 914, 
        "height": 91, 
        "width": 46
    }, 
    "=": {
        "y": 751, 
        "x": 813, 
        "height": 91, 
        "width": 48
    }, 
    "A": {
        "y": 1024, 
        "x": 0, 
        "height": 91, 
        "width": 56
    }, 
    "E": {
        "y": 1024, 
        "x": 228, 
        "height": 91, 
        "width": 54
    }, 
    "I": {
        "y": 1024, 
        "x": 454, 
        "height": 91, 
        "width": 23
    }, 
    "M": {
        "y": 1024, 
        "x": 619, 
        "height": 91, 
        "width": 68
    }, 
    "Q": {
        "y": 1024, 
        "x": 863, 
        "height": 91, 
        "width": 63
    }, 
    "U": {
        "y": 933, 
        "x": 104, 
        "height": 91, 
        "width": 59
    }, 
    "Y": {
        "y": 933, 
        "x": 348, 
        "height": 91, 
        "width": 54
    }, 
    "]": {
        "y": 751, 
        "x": 470, 
        "height": 91, 
        "width": 23
    }, 
    "a": {
        "y": 933, 
        "x": 452, 
        "height": 91, 
        "width": 46
    }, 
    "e": {
        "y": 933, 
        "x": 631, 
        "height": 91, 
        "width": 46
    }, 
    "i": {
        "y": 933, 
        "x": 795, 
        "height": 91, 
        "width": 19
    }, 
    "m": {
        "y": 933, 
        "x": 897, 
        "height": 91, 
        "width": 68
    }, 
    "q": {
        "y": 842, 
        "x": 92, 
        "height": 91, 
        "width": 46
    }, 
    "u": {
        "y": 842, 
        "x": 231, 
        "height": 91, 
        "width": 46
    }, 
    "y": {
        "y": 842, 
        "x": 418, 
        "height": 91, 
        "width": 41
    }, 
    "}": {
        "y": 751, 
        "x": 714, 
        "height": 91, 
        "width": 28
    }
}